README.md
setup.py
topsis_101703166_COE8/tops.py
topsis_101703166_COE8.egg-info/PKG-INFO
topsis_101703166_COE8.egg-info/SOURCES.txt
topsis_101703166_COE8.egg-info/dependency_links.txt
topsis_101703166_COE8.egg-info/requires.txt
topsis_101703166_COE8.egg-info/top_level.txt