Metadata-Version: 2.1
Name: topsis-101703166-COE8
Version: 1.0.0
Summary: A Python package to implement Topsis analysis
Home-page: https://github.com/DhritiJindal27/Topsis-Dhriti
Author: dhriti
Author-email: djindal612@gmail.com
License: MIT
Platform: UNKNOWN
Classifier: License :: OSI Approved :: MIT License
Classifier: Programming Language :: Python :: 3
Classifier: Programming Language :: Python :: 3.7
